zeke/__init__.py
zeke/commands.py
zeke/dnsops.py
zeke/zeke.py
zeke/zookeeper.py
zeke-0.2.1.dist-info/DESCRIPTION.rst
zeke-0.2.1.dist-info/METADATA
zeke-0.2.1.dist-info/RECORD
zeke-0.2.1.dist-info/WHEEL
zeke-0.2.1.dist-info/entry_points.txt
zeke-0.2.1.dist-info/metadata.json
zeke-0.2.1.dist-info/top_level.txt
