Metadata-Version: 2.0
Name: zeke
Version: 0.2.1
Summary: A command-line tool for Zookeeper that is a pleasure to use
Home-page: https://github.com/yodle/zeke
Author: Yodle
Author-email: mdrago@yodle.com
License: UNKNOWN
Platform: UNKNOWN
Classifier: Programming Language :: Python :: 2
Classifier: Programming Language :: Python :: 3
Classifier: Operating System :: POSIX
Classifier: Development Status :: 4 - Beta
Classifier: Intended Audience :: Developers
Classifier: Topic :: Utilities
Requires-Dist: dnspython3
Requires-Dist: kazoo
